testresources/__init__.py
testresources/tests/TestUtil.py
testresources/tests/__init__.py
testresources/tests/test_optimising_test_suite.py
testresources/tests/test_resource_graph.py
testresources/tests/test_resourced_test_case.py
testresources/tests/test_test_loader.py
testresources/tests/test_test_resource.py
testresources-2.0.0.dist-info/DESCRIPTION.rst
testresources-2.0.0.dist-info/METADATA
testresources-2.0.0.dist-info/RECORD
testresources-2.0.0.dist-info/WHEEL
testresources-2.0.0.dist-info/metadata.json
testresources-2.0.0.dist-info/pbr.json
testresources-2.0.0.dist-info/top_level.txt
