Metadata-Version: 2.0
Name: testresources
Version: 2.0.0
Summary: Testresources, a pyunit extension for managing expensive test resources
Home-page: https://launchpad.net/testresources
Author: Testresources developers
Author-email: https://launchpad.net/~testresources-developers
License: UNKNOWN
Platform: UNKNOWN
Requires-Dist: pbr (>=1.8)
Provides-Extra: test
Requires-Dist: docutils; extra == 'test'
Requires-Dist: fixtures; extra == 'test'
Requires-Dist: testtools; extra == 'test'
